boldi/_cli_version.py
boldi/cli.py
boldi_cli-0.9.7.dist-info/METADATA
boldi_cli-0.9.7.dist-info/WHEEL
boldi_cli-0.9.7.dist-info/entry_points.txt
boldi_cli-0.9.7.dist-info/RECORD
