Metadata-Version: 2.4
Name: boldi-cli
Version: 0.9.7
Summary: boldi.cli part of Boldi's Python libraries
Author-email: Boldizsár Palotás <boldizsar.palotas@gmail.com>
License: MIT
Requires-Python: >=3.10
Requires-Dist: boldi-ctx==0.9.7
Requires-Dist: boldi-plugins==0.9.7
Requires-Dist: rich
